{
  "players": [
    {
      "player_id": 0,
      "type": "circle",
      "bounding_box": {
        "x1": 487,
        "y1": 270,
        "x2": 528,
        "y2": 324
      },
      "center": {
        "x": 507,
        "y": 297
      },
      "cropped_image_path": "/Users/prathmeshgawali/playbook-backend/manim_outputs/31ff8c76-da98-4fa1-be92-b44786c7d002/circles/circle_0.png",
      "alphabet": null,
      "confidence": null
    },
    {
      "player_id": 1,
      "type": "circle",
      "bounding_box": {
        "x1": 693,
        "y1": 318,
        "x2": 737,
        "y2": 366
      },
      "center": {
        "x": 715,
        "y": 342
      },
      "cropped_image_path": "/Users/prathmeshgawali/playbook-backend/manim_outputs/31ff8c76-da98-4fa1-be92-b44786c7d002/circles/circle_1.png",
      "alphabet": "Y",
      "confidence": 0.8466
    },
    {
      "player_id": 2,
      "type": "circle",
      "bounding_box": {
        "x1": 390,
        "y1": 401,
        "x2": 431,
        "y2": 454
      },
      "center": {
        "x": 410,
        "y": 427
      },
      "cropped_image_path": "/Users/prathmeshgawali/playbook-backend/manim_outputs/31ff8c76-da98-4fa1-be92-b44786c7d002/circles/circle_2.png",
      "alphabet": "Q",
      "confidence": 0.7358
    },
    {
      "player_id": 3,
      "type": "circle",
      "bounding_box": {
        "x1": 443,
        "y1": 270,
        "x2": 482,
        "y2": 324
      },
      "center": {
        "x": 462,
        "y": 297
      },
      "cropped_image_path": "/Users/prathmeshgawali/playbook-backend/manim_outputs/31ff8c76-da98-4fa1-be92-b44786c7d002/circles/circle_3.png",
      "alphabet": null,
      "confidence": null
    },
    {
      "player_id": 4,
      "type": "circle",
      "bounding_box": {
        "x1": 344,
        "y1": 271,
        "x2": 385,
        "y2": 323
      },
      "center": {
        "x": 364,
        "y": 297
      },
      "cropped_image_path": "/Users/prathmeshgawali/playbook-backend/manim_outputs/31ff8c76-da98-4fa1-be92-b44786c7d002/circles/circle_4.png",
      "alphabet": null,
      "confidence": null
    },
    {
      "player_id": 5,
      "type": "circle",
      "bounding_box": {
        "x1": 297,
        "y1": 271,
        "x2": 340,
        "y2": 323
      },
      "center": {
        "x": 318,
        "y": 297
      },
      "cropped_image_path": "/Users/prathmeshgawali/playbook-backend/manim_outputs/31ff8c76-da98-4fa1-be92-b44786c7d002/circles/circle_5.png",
      "alphabet": null,
      "confidence": null
    },
    {
      "player_id": 6,
      "type": "circle",
      "bounding_box": {
        "x1": 295,
        "y1": 402,
        "x2": 336,
        "y2": 451
      },
      "center": {
        "x": 315,
        "y": 426
      },
      "cropped_image_path": "/Users/prathmeshgawali/playbook-backend/manim_outputs/31ff8c76-da98-4fa1-be92-b44786c7d002/circles/circle_6.png",
      "alphabet": "H",
      "confidence": 0.7552
    },
    {
      "player_id": 7,
      "type": "circle",
      "bounding_box": {
        "x1": 795,
        "y1": 318,
        "x2": 837,
        "y2": 366
      },
      "center": {
        "x": 816,
        "y": 342
      },
      "cropped_image_path": "/Users/prathmeshgawali/playbook-backend/manim_outputs/31ff8c76-da98-4fa1-be92-b44786c7d002/circles/circle_7.png",
      "alphabet": "Z",
      "confidence": 0.7438
    },
    {
      "player_id": 8,
      "type": "circle",
      "bounding_box": {
        "x1": 251,
        "y1": 271,
        "x2": 289,
        "y2": 320
      },
      "center": {
        "x": 270,
        "y": 295
      },
      "cropped_image_path": "/Users/prathmeshgawali/playbook-backend/manim_outputs/31ff8c76-da98-4fa1-be92-b44786c7d002/circles/circle_8.png",
      "alphabet": "T",
      "confidence": 0.884
    },
    {
      "player_id": 9,
      "type": "square",
      "bounding_box": {
        "x1": 388,
        "y1": 257,
        "x2": 437,
        "y2": 333
      },
      "center": {
        "x": 412,
        "y": 295
      },
      "alphabet": null,
      "confidence": null
    },
    {
      "player_id": 9,
      "type": "circle",
      "bounding_box": {
        "x1": 577,
        "y1": 275,
        "x2": 620,
        "y2": 324
      },
      "center": {
        "x": 598,
        "y": 299
      },
      "cropped_image_path": "/Users/prathmeshgawali/playbook-backend/manim_outputs/31ff8c76-da98-4fa1-be92-b44786c7d002/circles/circle_9.png",
      "alphabet": "X",
      "confidence": 0.7822
    }
  ]
}